cleansummary/__init__.py
cleansummary-0.0.5.dist-info/METADATA
cleansummary-0.0.5.dist-info/WHEEL
cleansummary-0.0.5.dist-info/top_level.txt
cleansummary-0.0.5.dist-info/RECORD
