Metadata-Version: 2.1
Name: cleansummary
Version: 0.0.5
Summary: A simple package to get statistical summary of a pandas dataframe
Home-page: UNKNOWN
Author: Francis W. Onyango
Author-email: fonyango.w@gmail.com
License: MIT
Keywords: cleansummary
Platform: UNKNOWN
Classifier: Development Status :: 4 - Beta
Classifier: Intended Audience :: Developers
Classifier: Operating System :: OS Independent
Classifier: License :: OSI Approved :: MIT License
Classifier: Programming Language :: Python :: 3
